stario/.DS_Store
stario/__init__.py
stario/cli/__init__.py
stario/cli/__main__.py
stario/cli/templates/hello-world/main.py
stario/cli/templates/hello-world/static/js/datastar.js
stario/cli/templates/tiles/main.py
stario/cli/templates/tiles/static/css/style.css
stario/cli/templates/tiles/static/js/datastar.js
stario/datastar/__init__.py
stario/datastar/actions.py
stario/datastar/attributes.py
stario/datastar/format.py
stario/datastar/parse.py
stario/datastar/signals.py
stario/datastar/sse.py
stario/exceptions.py
stario/html/__init__.py
stario/html/core.py
stario/html/safestring.py
stario/html/types.py
stario/http/__init__.py
stario/http/app.py
stario/http/headers.py
stario/http/protocol.py
stario/http/request.py
stario/http/router.py
stario/http/staticassets.py
stario/http/types.py
stario/http/writer.py
stario/py.typed
stario/relay.py
stario/telemetry/__init__.py
stario/telemetry/core.py
stario/telemetry/json.py
stario/telemetry/rich.py
stario/testing.py
stario/toys.py
stario-2.0.5.dist-info/WHEEL
stario-2.0.5.dist-info/entry_points.txt
stario-2.0.5.dist-info/METADATA
stario-2.0.5.dist-info/RECORD
