Metadata-Version: 2.3
Name: stario
Version: 2.0.5
Summary: Stario - High-performance Python web framework
Author: Adam Bobowski
Author-email: Adam Bobowski <adam.bobowski@wratilabs.com>
Requires-Dist: aiofiles>=24.1.0
Requires-Dist: brotli>=1.1.0
Requires-Dist: click>=8.1.0
Requires-Dist: httptools>=0.7.1
Requires-Dist: rich>=14.1.0
Requires-Dist: xxhash>=3.5.0
Requires-Python: >=3.14
